<?xml version="1.0" encoding="UTF-8"?>
<!DOCTYPE mapper PUBLIC "-//mybatis.org//DTD Mapper 3.0//EN" "http://mybatis.org/dtd/mybatis-3-mapper.dtd">
<mapper namespace="com.wangchen.example.springboot.dao.GirlInfoMapper">
  <resultMap id="BaseResultMap" type="com.wangchen.example.springboot.entity.GirlInfo">
    <!--
      WARNING - @mbggenerated
      This element is automatically generated by MyBatis Generator, do not modify.
    -->
    <id column="id" jdbcType="INTEGER" property="id" />
    <result column="name" jdbcType="VARCHAR" property="name" />
    <result column="nickname" jdbcType="VARCHAR" property="nickname" />
    <result column="age" jdbcType="TINYINT" property="age" />
    <result column="height" jdbcType="TINYINT" property="height" />
    <result column="weight" jdbcType="TINYINT" property="weight" />
    <result column="chest" jdbcType="VARCHAR" property="chest" />
    <result column="waist" jdbcType="TINYINT" property="waist" />
    <result column="hip" jdbcType="TINYINT" property="hip" />
    <result column="shoe_size" jdbcType="TINYINT" property="shoeSize" />
    <result column="hair_style" jdbcType="VARCHAR" property="hairStyle" />
    <result column="hari_color" jdbcType="VARCHAR" property="hariColor" />
    <result column="adress" jdbcType="VARCHAR" property="adress" />
    <result column="phone" jdbcType="VARCHAR" property="phone" />
    <result column="interest" jdbcType="VARCHAR" property="interest" />
    <result column="advatage" jdbcType="VARCHAR" property="advatage" />
    <result column="disadvatage" jdbcType="VARCHAR" property="disadvatage" />
    <result column="update_time" jdbcType="TIMESTAMP" property="updateTime" />
    <result column="create_time" jdbcType="TIMESTAMP" property="createTime" />
  </resultMap>
  <sql id="Base_Column_List">
    <!--
      WARNING - @mbggenerated
      This element is automatically generated by MyBatis Generator, do not modify.
    -->
    id, name, nickname, age, height, weight, chest, waist, hip, shoe_size, hair_style, 
    hari_color, adress, phone, interest, advatage, disadvatage, update_time, create_time
  </sql>
  <select id="selectByPrimaryKey" parameterType="java.lang.Integer" resultMap="BaseResultMap">
    <!--
      WARNING - @mbggenerated
      This element is automatically generated by MyBatis Generator, do not modify.
    -->
    select 
    <include refid="Base_Column_List" />
    from girl_info
    where id = #{id,jdbcType=INTEGER}
  </select>
  <delete id="deleteByPrimaryKey" parameterType="java.lang.Integer">
    <!--
      WARNING - @mbggenerated
      This element is automatically generated by MyBatis Generator, do not modify.
    -->
    delete from girl_info
    where id = #{id,jdbcType=INTEGER}
  </delete>
  <insert id="insert" parameterType="com.wangchen.example.springboot.entity.GirlInfo">
    <!--
      WARNING - @mbggenerated
      This element is automatically generated by MyBatis Generator, do not modify.
    -->
    insert into girl_info (id, name, nickname, 
      age, height, weight, 
      chest, waist, hip, 
      shoe_size, hair_style, hari_color, 
      adress, phone, interest, 
      advatage, disadvatage, update_time, 
      create_time)
    values (#{id,jdbcType=INTEGER}, #{name,jdbcType=VARCHAR}, #{nickname,jdbcType=VARCHAR}, 
      #{age,jdbcType=TINYINT}, #{height,jdbcType=TINYINT}, #{weight,jdbcType=TINYINT}, 
      #{chest,jdbcType=VARCHAR}, #{waist,jdbcType=TINYINT}, #{hip,jdbcType=TINYINT}, 
      #{shoeSize,jdbcType=TINYINT}, #{hairStyle,jdbcType=VARCHAR}, #{hariColor,jdbcType=VARCHAR}, 
      #{adress,jdbcType=VARCHAR}, #{phone,jdbcType=VARCHAR}, #{interest,jdbcType=VARCHAR}, 
      #{advatage,jdbcType=VARCHAR}, #{disadvatage,jdbcType=VARCHAR}, #{updateTime,jdbcType=TIMESTAMP}, 
      #{createTime,jdbcType=TIMESTAMP})
  </insert>
  <insert id="insertSelective" parameterType="com.wangchen.example.springboot.entity.GirlInfo">
    <!--
      WARNING - @mbggenerated
      This element is automatically generated by MyBatis Generator, do not modify.
    -->
    insert into girl_info
    <trim prefix="(" suffix=")" suffixOverrides=",">
      <if test="id != null">
        id,
      </if>
      <if test="name != null">
        name,
      </if>
      <if test="nickname != null">
        nickname,
      </if>
      <if test="age != null">
        age,
      </if>
      <if test="height != null">
        height,
      </if>
      <if test="weight != null">
        weight,
      </if>
      <if test="chest != null">
        chest,
      </if>
      <if test="waist != null">
        waist,
      </if>
      <if test="hip != null">
        hip,
      </if>
      <if test="shoeSize != null">
        shoe_size,
      </if>
      <if test="hairStyle != null">
        hair_style,
      </if>
      <if test="hariColor != null">
        hari_color,
      </if>
      <if test="adress != null">
        adress,
      </if>
      <if test="phone != null">
        phone,
      </if>
      <if test="interest != null">
        interest,
      </if>
      <if test="advatage != null">
        advatage,
      </if>
      <if test="disadvatage != null">
        disadvatage,
      </if>
      <if test="updateTime != null">
        update_time,
      </if>
      <if test="createTime != null">
        create_time,
      </if>
    </trim>
    <trim prefix="values (" suffix=")" suffixOverrides=",">
      <if test="id != null">
        #{id,jdbcType=INTEGER},
      </if>
      <if test="name != null">
        #{name,jdbcType=VARCHAR},
      </if>
      <if test="nickname != null">
        #{nickname,jdbcType=VARCHAR},
      </if>
      <if test="age != null">
        #{age,jdbcType=TINYINT},
      </if>
      <if test="height != null">
        #{height,jdbcType=TINYINT},
      </if>
      <if test="weight != null">
        #{weight,jdbcType=TINYINT},
      </if>
      <if test="chest != null">
        #{chest,jdbcType=VARCHAR},
      </if>
      <if test="waist != null">
        #{waist,jdbcType=TINYINT},
      </if>
      <if test="hip != null">
        #{hip,jdbcType=TINYINT},
      </if>
      <if test="shoeSize != null">
        #{shoeSize,jdbcType=TINYINT},
      </if>
      <if test="hairStyle != null">
        #{hairStyle,jdbcType=VARCHAR},
      </if>
      <if test="hariColor != null">
        #{hariColor,jdbcType=VARCHAR},
      </if>
      <if test="adress != null">
        #{adress,jdbcType=VARCHAR},
      </if>
      <if test="phone != null">
        #{phone,jdbcType=VARCHAR},
      </if>
      <if test="interest != null">
        #{interest,jdbcType=VARCHAR},
      </if>
      <if test="advatage != null">
        #{advatage,jdbcType=VARCHAR},
      </if>
      <if test="disadvatage != null">
        #{disadvatage,jdbcType=VARCHAR},
      </if>
      <if test="updateTime != null">
        #{updateTime,jdbcType=TIMESTAMP},
      </if>
      <if test="createTime != null">
        #{createTime,jdbcType=TIMESTAMP},
      </if>
    </trim>
  </insert>
  <update id="updateByPrimaryKeySelective" parameterType="com.wangchen.example.springboot.entity.GirlInfo">
    <!--
      WARNING - @mbggenerated
      This element is automatically generated by MyBatis Generator, do not modify.
    -->
    update girl_info
    <set>
      <if test="name != null">
        name = #{name,jdbcType=VARCHAR},
      </if>
      <if test="nickname != null">
        nickname = #{nickname,jdbcType=VARCHAR},
      </if>
      <if test="age != null">
        age = #{age,jdbcType=TINYINT},
      </if>
      <if test="height != null">
        height = #{height,jdbcType=TINYINT},
      </if>
      <if test="weight != null">
        weight = #{weight,jdbcType=TINYINT},
      </if>
      <if test="chest != null">
        chest = #{chest,jdbcType=VARCHAR},
      </if>
      <if test="waist != null">
        waist = #{waist,jdbcType=TINYINT},
      </if>
      <if test="hip != null">
        hip = #{hip,jdbcType=TINYINT},
      </if>
      <if test="shoeSize != null">
        shoe_size = #{shoeSize,jdbcType=TINYINT},
      </if>
      <if test="hairStyle != null">
        hair_style = #{hairStyle,jdbcType=VARCHAR},
      </if>
      <if test="hariColor != null">
        hari_color = #{hariColor,jdbcType=VARCHAR},
      </if>
      <if test="adress != null">
        adress = #{adress,jdbcType=VARCHAR},
      </if>
      <if test="phone != null">
        phone = #{phone,jdbcType=VARCHAR},
      </if>
      <if test="interest != null">
        interest = #{interest,jdbcType=VARCHAR},
      </if>
      <if test="advatage != null">
        advatage = #{advatage,jdbcType=VARCHAR},
      </if>
      <if test="disadvatage != null">
        disadvatage = #{disadvatage,jdbcType=VARCHAR},
      </if>
      <if test="updateTime != null">
        update_time = #{updateTime,jdbcType=TIMESTAMP},
      </if>
      <if test="createTime != null">
        create_time = #{createTime,jdbcType=TIMESTAMP},
      </if>
    </set>
    where id = #{id,jdbcType=INTEGER}
  </update>
  <update id="updateByPrimaryKey" parameterType="com.wangchen.example.springboot.entity.GirlInfo">
    <!--
      WARNING - @mbggenerated
      This element is automatically generated by MyBatis Generator, do not modify.
    -->
    update girl_info
    set name = #{name,jdbcType=VARCHAR},
      nickname = #{nickname,jdbcType=VARCHAR},
      age = #{age,jdbcType=TINYINT},
      height = #{height,jdbcType=TINYINT},
      weight = #{weight,jdbcType=TINYINT},
      chest = #{chest,jdbcType=VARCHAR},
      waist = #{waist,jdbcType=TINYINT},
      hip = #{hip,jdbcType=TINYINT},
      shoe_size = #{shoeSize,jdbcType=TINYINT},
      hair_style = #{hairStyle,jdbcType=VARCHAR},
      hari_color = #{hariColor,jdbcType=VARCHAR},
      adress = #{adress,jdbcType=VARCHAR},
      phone = #{phone,jdbcType=VARCHAR},
      interest = #{interest,jdbcType=VARCHAR},
      advatage = #{advatage,jdbcType=VARCHAR},
      disadvatage = #{disadvatage,jdbcType=VARCHAR},
      update_time = #{updateTime,jdbcType=TIMESTAMP},
      create_time = #{createTime,jdbcType=TIMESTAMP}
    where id = #{id,jdbcType=INTEGER}
  </update>
</mapper>